{
  "project": "honeydew2026",
  "current_phase": "S9",
  "phase_history": {
    "R0": {"status": "complete", "issue_id": null},
    "R1": {"status": "complete", "issue_id": null},
    "S1": {"status": "complete", "issue_id": null},
    "S1.5": {"status": "complete", "issue_id": "7dea13c9-780a-4570-9e96-bded564c3775", "completed_at": "2026-04-15T04:50:00Z"},
    "S2": {"status": "complete", "issue_id": "58ed66ab-ca4e-4f33-b070-c6deb5cb3fb7", "completed_at": "2026-04-15T09:00:00Z", "decision": "PASS"},
    "S3": {"status": "complete", "issue_id": "VEX-832", "completed_at": "2026-04-27T00:00:00Z", "decision": "done"},
    "S4": {"status": "complete", "issue_id": null, "completed_at": "2026-04-16T14:20:00Z", "prs_merged": ["PR #2-#6 all merged"], "note": "All 5 S4 PRs merged per gh pr list"},
    "S5": {"status": "complete", "issue_id": null, "completed_at": "2026-04-16T14:30:00Z", "note": "Merged to main"},
    "S5.5": {"status": "skipped", "reason": "CEO directive - skip to launch"},
    "S6": {"status": "skipped", "reason": "CEO directive - skip to launch"},
    "S7": {"status": "skipped", "reason": "CEO directive - skip to launch"},
    "S8": {"status": "complete", "issue_id": "VEX-838", "completed_at": "2026-04-22T18:00:00Z"},
    "S9": {"status": "in_progress", "issue_id": null, "assigned_to": "DevOps-Engineer"},
    "S10": {"status": "pending", "issue_id": null}
  },
  "backend": {
    "status": "running",
    "port": 8018,
    "pid": null,
    "database": "in-memory (mock data)"
  },
  "frontend": {
    "status": "source_exists",
    "build": "fail",
    "dist": "exists",
    "source": "exists_but_broken",
    "note": "Frontend source exists on main branch but build fails. Issues: TailwindCSS @tailwindcss/postcss missing, AchievementBadge component missing"
  },
  "s2_review": {
    "decision": "PASS",
    "reviewer": "Technical-Director",
    "review_doc": "S2_REVIEW_COUNCIL_GATE.md",
    "deviations_noted": ["Python/FastAPI instead of Node/Express", "SQLite instead of PostgreSQL", "JSX instead of TypeScript"],
    "reason": "Core features functional, tech stack deviations acceptable"
  },
  "s3_review": {
    "decision": "done",
    "reviewer": "Opencode-Agent",
    "review_doc": "opencode1.md",
    "issues_found": ["Frontend source missing - cannot rebuild", "No database persistence", "JWT secret hardcoded fallback", "CORS wide open"],
    "blocking_issues": false
  },
  "s8_final_report": {
    "decision": "complete",
    "reviewer": "Google-Jules-Merge-Agent",
    "review_doc": "S8-final-report.md",
    "note": "Frontend dist/ exists but source missing. Backend healthy on port 8018."
  },
  "last_updated": "2026-04-23T06:30:00Z",
  "updated_by": "Google-Jules-Merge-Agent",
  "note": "Fixed pipeline-status: S4/S5 now correctly marked complete. S9 is next phase (DevOps deployment)."
}
